entity_search/__init__.py
entity_search/adjacency.py
entity_search/bfs.py
entity_search/evaluation.py
entity_search/interfaces.py
entity_search/katz.py
entity_search/math.py
entity_search/multitext.py
entity_search/notebook.py
entity_search/preprocessing.py
entity_search/queries.py
entity_search/results.py
entity_search/run.py
entity_search/runtime.py
entity_search/smooth.py
entity_search/string.py
entity_search/utilities.py
entity_search/diffusion/__init__.py
entity_search/diffusion/power_iteration.py
entity_search/diffusion/truncate.py
entity_search/multitext/__init__.py
entity_search/multitext/corpus.py
entity_search/multitext/indices.py
entity_search/multitext/similarities.py
entity_search/multitext/transform.py
entity_search/tests/__init__.py
entity_search/tests/test_multitext.py
entity_search/tests/test_utilities.py
tests/__init__.py
tests/helpers.py
tests/benchmarks/__init__.py
tests/benchmarks/helpers.py
tests/benchmarks/test_diffusion.py
tests/benchmarks/test_indices.py
tests/benchmarks/test_math.py
tests/benchmarks/test_run.py
tests/benchmarks/test_similarities.py
tests/dev/__init__.py
tests/dev/helpers.py
tests/dev/test_adjacency.py
tests/dev/test_corpus.py
tests/dev/test_diffusion.py
tests/dev/test_indices.py
tests/dev/test_math.py
tests/dev/test_results.py
tests/dev/test_run.py
tests/dev/test_similarities.py
tests/dev/test_smooth.py
tests/dev/test_transform.py
tests/tes/__init__.py
tests/tes/helpers.py
tests/tes/test_adjacency.py
tests/tes/test_corpus.py
tests/tes/test_diffusion.py
tests/tes/test_indices.py
tests/tes/test_math.py
tests/tes/test_queries.py
tests/tes/test_results.py
tests/tes/test_run.py
tests/tes/test_similarities.py
tests/tes/test_utilities.py
entity_search-0.0.4.dist-info/METADATA
entity_search-0.0.4.dist-info/WHEEL
entity_search-0.0.4.dist-info/entry_points.txt
entity_search-0.0.4.dist-info/top_level.txt
entity_search-0.0.4.dist-info/RECORD
