Metadata-Version: 2.1
Name: entity-search
Version: 0.0.4
Summary: Entity Search
Home-page: https://github.com/ptorrest/entity-search
Author: Pablo Torres
Author-email: pablo.torres@insight-centre.org
License: GNU
Platform: UNKNOWN
Classifier: Programming Language :: Python :: 3.6
Requires-Dist: colorlog
Requires-Dist: gensim
Requires-Dist: krovetz
Requires-Dist: matplotlib
Requires-Dist: nltk
Requires-Dist: numba
Requires-Dist: numpy
Requires-Dist: pandas
Requires-Dist: scipy
Requires-Dist: sparse
